Workbook

Sheet Cover
B2: LOAN AMORTIZATION & CREDIT RISK DASHBOARD
B3: Built by Kartik Joshi | Finance · FP&A · AML/KYC · FMVA® · CBCA® · FPAP™
B5: Overview
B6: This workbook demonstrates a complete loan amortization engine with credit-risk scoring. Inputs flow through PMT-based amortization, a VLOOKUP/HLOOKUP rate grid, INDEX/MATCH risk tiering, and an automated VBA macro that rebuilds the schedule on any input change. Contains data validation, conditional formatting, named ranges, and a dashboard summary card — the full stack a financial analyst uses daily.
B12: Techniques Demonstrated
B13: VLOOKUP | C13: Rate lookup by credit score band
B14: HLOOKUP | C14: Horizontal rate grid by loan term
B15: INDEX/MATCH | C15: Two-way risk tier lookup
B16: PMT / IPMT / PPMT | C16: Amortization schedule
B17: IFS / SWITCH | C17: Risk tier classification
B18: Named Ranges | C18: LoanAmt, Rate, Term, Score
B19: Data Validation | C19: Dropdown lists on inputs
B20: Conditional Formatting | C20: Payment & balance heatmap
B21: VBA Macro | C21: Auto-rebuild schedule on change
B22: Tables | C22: Structured amortization table

Sheet Inputs
B2: LOAN INPUTS
B4: Borrower Name | C4: Sample Borrower | D4: Free text
B5: Loan Amount ($) | C5: 350000 | D5: Principal amount
B6: Annual Interest Rate | C6: 0.0625 | D6: Enter as decimal (6.25% = 0.0625)
B7: Loan Term (Years) | C7: 25 | D7: Dropdown: 5, 10, 15, 20, 25, 30
B8: Credit Score | C8: 720 | D8: 300–850
B9: Annual Income ($) | C9: 95000 | D9: Gross annual income
B10: Existing Monthly Debt ($) | C10: 850 | D10: Sum of other obligations
B11: Property Value ($) | C11: 425000 | D11: For LTV calculation
B14: DERIVED METRICS
B15: Monthly Payment (PMT) | C15: =PMT(IntRate/12, TermYrs*12, -LoanAmt) -> 2308.8428
B16: Total Payments ($) | C16: =C15*TermYrs*12 -> 692652.85
B17: Total Interest ($) | C17: =C16-LoanAmt -> 342652.85
B18: Loan-to-Value (LTV) | C18: =LoanAmt/PropVal -> 0.82352941
B19: Debt-to-Income (DTI) | C19: =(C15+OtherDebt)*12/Income -> 0.39901173
B20: Rate via VLOOKUP | C20: =VLOOKUP(Score, RateGrid!$B$4:$C$9, 2, TRUE()) -> 0.0625
B21: Rate via HLOOKUP | C21: =HLOOKUP(TermYrs, RateGrid!$F$3:$K$4, 2, FALSE()) -> 0.0625
B22: Risk Tier (INDEX/MATCH) | C22: =INDEX(RateGrid!$B$4:$D$9, MATCH(Score, RateGrid!$B$4:$B$9, 1), 3) -> Super Prime
B23: Approval Flag (dashboard) | C23: =IF(AND(Score>=680,C19<=0.4,C18<=0.8),"APPROVE",IF(AND(Score>=640,C19<=0.45),"REVIEW","DECLINE")) -> REVIEW

Sheet RateGrid
B2: RATE GRID — VLOOKUP (Score → Rate) | F2: RATE GRID — HLOOKUP (Term → Rate)
B3: Min Score | C3: Rate | D3: Risk Tier | F3: 5 | G3: 10 | H3: 15 | I3: 20 | J3: 25 | K3: 30
B4: 300 | C4: 0.125 | D4: Subprime | F4: 0.045 | G4: 0.0525 | H4: 0.06 | I4: 0.065 | J4: 0.0625 | K4: 0.07
B5: 580 | C5: 0.105 | D5: Near Prime
B6: 640 | C6: 0.0875 | D6: Standard | F6: Grid Notes
B7: 680 | C7: 0.075 | D7: Prime | F7: VLOOKUP uses TRUE (approximate match) to find the first score band the credit score falls into. HLOOKUP uses FALSE (exact match) to pick the rate for the specified loan term. In production this grid would be sourced from treasury / risk — here it's a realistic spread for illustration.
B8: 720 | C8: 0.0625 | D8: Super Prime
B9: 780 | C9: 0.0525 | D9: Elite

Sheet Schedule
B2: AMORTIZATION SCHEDULE
B4: Period | C4: Payment | D4: Interest | E4: Principal | F4: Balance
B5: 1 | C5: =IF(B5<=TermYrs*12, -PMT(IntRate/12, TermYrs*12, LoanAmt), "") -> 2308.8428 | D5: =IF(B5<=TermYrs*12, -IPMT(IntRate/12, B5, TermYrs*12, LoanAmt), "") -> 1822.9167 | E5: =IF(B5<=TermYrs*12, -PPMT(IntRate/12, B5, TermYrs*12, LoanAmt), "") -> 485.92616 | F5: =IF(B5<=TermYrs*12, LoanAmt-SUMIFS($E$5:E5, $B$5:B5, "<="&B5), "") -> 349514.07
B6: 2 | C6: =IF(B6<=TermYrs*12, -PMT(IntRate/12, TermYrs*12, LoanAmt), "") -> 2308.8428 | D6: =IF(B6<=TermYrs*12, -IPMT(IntRate/12, B6, TermYrs*12, LoanAmt), "") -> 1820.3858 | E6: =IF(B6<=TermYrs*12, -PPMT(IntRate/12, B6, TermYrs*12, LoanAmt), "") -> 488.45702 | F6: =IF(B6<=TermYrs*12, LoanAmt-SUMIFS($E$5:E6, $B$5:B6, "<="&B6), "") -> 349025.62
B7: 3 | C7: =IF(B7<=TermYrs*12, -PMT(IntRate/12, TermYrs*12, LoanAmt), "") -> 2308.8428 | D7: =IF(B7<=TermYrs*12, -IPMT(IntRate/12, B7, TermYrs*12, LoanAmt), "") -> 1817.8418 | E7: =IF(B7<=TermYrs*12, -PPMT(IntRate/12, B7, TermYrs*12, LoanAmt), "") -> 491.00107 | F7: =IF(B7<=TermYrs*12, LoanAmt-SUMIFS($E$5:E7, $B$5:B7, "<="&B7), "") -> 348534.62
B8: 4 | C8: =IF(B8<=TermYrs*12, -PMT(IntRate/12, TermYrs*12, LoanAmt), "") -> 2308.8428 | D8: =IF(B8<=TermYrs*12, -IPMT(IntRate/12, B8, TermYrs*12, LoanAmt), "") -> 1815.2845 | E8: =IF(B8<=TermYrs*12, -PPMT(IntRate/12, B8, TermYrs*12, LoanAmt), "") -> 493.55837 | F8: =IF(B8<=TermYrs*12, LoanAmt-SUMIFS($E$5:E8, $B$5:B8, "<="&B8), "") -> 348041.06
B9: 5 | C9: =IF(B9<=TermYrs*12, -PMT(IntRate/12, TermYrs*12, LoanAmt), "") -> 2308.8428 | D9: =IF(B9<=TermYrs*12, -IPMT(IntRate/12, B9, TermYrs*12, LoanAmt), "") -> 1812.7138 | E9: =IF(B9<=TermYrs*12, -PPMT(IntRate/12, B9, TermYrs*12, LoanAmt), "") -> 496.12898 | F9: =IF(B9<=TermYrs*12, LoanAmt-SUMIFS($E$5:E9, $B$5:B9, "<="&B9), "") -> 347544.93
B10: 6 | C10: =IF(B10<=TermYrs*12, -PMT(IntRate/12, TermYrs*12, LoanAmt), "") -> 2308.8428 | D10: =IF(B10<=TermYrs*12, -IPMT(IntRate/12, B10, TermYrs*12, LoanAmt), "") -> 1810.1298 | E10: =IF(B10<=TermYrs*12, -PPMT(IntRate/12, B10, TermYrs*12, LoanAmt), "") -> 498.71299 | F10: =IF(B10<=TermYrs*12, LoanAmt-SUMIFS($E$5:E10, $B$5:B10, "<="&B10), "") -> 347046.22
B11: 7 | C11: =IF(B11<=TermYrs*12, -PMT(IntRate/12, TermYrs*12, LoanAmt), "") -> 2308.8428 | D11: =IF(B11<=TermYrs*12, -IPMT(IntRate/12, B11, TermYrs*12, LoanAmt), "") -> 1807.5324 | E11: =IF(B11<=TermYrs*12, -PPMT(IntRate/12, B11, TermYrs*12, LoanAmt), "") -> 501.31045 | F11: =IF(B11<=TermYrs*12, LoanAmt-SUMIFS($E$5:E11, $B$5:B11, "<="&B11), "") -> 346544.9
B12: 8 | C12: =IF(B12<=TermYrs*12, -PMT(IntRate/12, TermYrs*12, LoanAmt), "") -> 2308.8428 | D12: =IF(B12<=TermYrs*12, -IPMT(IntRate/12, B12, TermYrs*12, LoanAmt), "") -> 1804.9214 | E12: =IF(B12<=TermYrs*12, -PPMT(IntRate/12, B12, TermYrs*12, LoanAmt), "") -> 503.92144 | F12: =IF(B12<=TermYrs*12, LoanAmt-SUMIFS($E$5:E12, $B$5:B12, "<="&B12), "") -> 346040.98
B13: 9 | C13: =IF(B13<=TermYrs*12, -PMT(IntRate/12, TermYrs*12, LoanAmt), "") -> 2308.8428 | D13: =IF(B13<=TermYrs*12, -IPMT(IntRate/12, B13, TermYrs*12, LoanAmt), "") -> 1802.2968 | E13: =IF(B13<=TermYrs*12, -PPMT(IntRate/12, B13, TermYrs*12, LoanAmt), "") -> 506.54603 | F13: =IF(B13<=TermYrs*12, LoanAmt-SUMIFS($E$5:E13, $B$5:B13, "<="&B13), "") -> 345534.44
B14: 10 | C14: =IF(B14<=TermYrs*12, -PMT(IntRate/12, TermYrs*12, LoanAmt), "") -> 2308.8428 | D14: =IF(B14<=TermYrs*12, -IPMT(IntRate/12, B14, TermYrs*12, LoanAmt), "") -> 1799.6585 | E14: =IF(B14<=TermYrs*12, -PPMT(IntRate/12, B14, TermYrs*12, LoanAmt), "") -> 509.1843 | F14: =IF(B14<=TermYrs*12, LoanAmt-SUMIFS($E$5:E14, $B$5:B14, "<="&B14), "") -> 345025.25
B15: 11 | C15: =IF(B15<=TermYrs*12, -PMT(IntRate/12, TermYrs*12, LoanAmt), "") -> 2308.8428 | D15: =IF(B15<=TermYrs*12, -IPMT(IntRate/12, B15, TermYrs*12, LoanAmt), "") -> 1797.0065 | E15: =IF(B15<=TermYrs*12, -PPMT(IntRate/12, B15, TermYrs*12, LoanAmt), "") -> 511.8363 | F15: =IF(B15<=TermYrs*12, LoanAmt-SUMIFS($E$5:E15, $B$5:B15, "<="&B15), "") -> 344513.42
B16: 12 | C16: =IF(B16<=TermYrs*12, -PMT(IntRate/12, TermYrs*12, LoanAmt), "") -> 2308.8428 | D16: =IF(B16<=TermYrs*12, -IPMT(IntRate/12, B16, TermYrs*12, LoanAmt), "") -> 1794.3407 | E16: =IF(B16<=TermYrs*12, -PPMT(IntRate/12, B16, TermYrs*12, LoanAmt), "") -> 514.50211 | F16: =IF(B16<=TermYrs*12, LoanAmt-SUMIFS($E$5:E16, $B$5:B16, "<="&B16), "") -> 343998.91
... B364: 360 | C364: =IF(B364<=TermYrs*12, -PMT(IntRate/12, TermYrs*12, LoanAmt), "") | D364: =IF(B364<=TermYrs*12, -IPMT(IntRate/12, B364, TermYrs*12, LoanAmt), "") | E364: =IF(B364<=TermYrs*12, -PPMT(IntRate/12, B364, TermYrs*12, LoanAmt), "") | F364: =IF(B364<=TermYrs*12, LoanAmt-SUMIFS($E$5:E364, $B$5:B364, "<="&B364), "")

Sheet Dashboard
B2: LOAN DASHBOARD
B3: Live KPIs from Inputs + Rate Grid + Schedule
B5: Monthly Payment | D5: Total Interest | F5: LTV Ratio | H5: DTI Ratio
B6: =Inputs!C15 -> 2308.8428 | D6: =Inputs!C17 -> 342652.85 | F6: =Inputs!C18 -> 0.82352941 | H6: =Inputs!C19 -> 0.39901173
B10: RISK ASSESSMENT
B11: Credit Score | C11: =Score -> 720
B12: Risk Tier | C12: =Inputs!C22 -> Super Prime
B13: Applied Rate (VLOOKUP) | C13: =Inputs!C20 -> 0.0625
B14: Approval Flag (IF/AND) | C14: =IF(AND(Score>=680,Inputs!C19<=0.4,Inputs!C18<=0.8),"APPROVE",IF(AND(Score>=640,Inputs!C19<=0.45),"REVIEW","DECLINE")) -> REVIEW
B15: Recommended Action | C15: =IF(Inputs!C23="APPROVE","Proceed to docs & disbursement",IF(Inputs!C23="REVIEW","Escalate to credit committee","Decline or restructure")) -> Escalate to credit committee

Sheet VBA_Code
B2: VBA MACRO — AutoRefresh & Stress Test
B3: The following VBA module is also provided as LoanMacros.bas. To enable: open this file as .xlsm, press Alt+F11, right-click the project, Import File → select LoanMacros.bas. Run macros via Alt+F8.
B5: Option Explicit ' ============================================================ ' LoanMacros.bas — Kartik Joshi ' Portfolio demo: auto-refresh, stress test, and rate shock ' ============================================================ ' Automatically recalculate and log when any input changes Public Sub AutoRefreshSchedule() Application.ScreenUpdating = False Application.Calculation = xlCalculationAutomatic ThisWorkbook.Worksheets("Schedule").Calculate ThisWorkbook.Worksheets("Dashboard").Calculate MsgBox "Amortization schedule and dashboard refreshed.", vbInformation, "Loan Model" Application.ScreenUpdating = True End Sub ' Run a +/- 200 bps rate stress test and write results Public Sub RunRateStressTest() Dim ws As Worksheet, stressWs As Worksheet Dim baseRate As Double, i As Integer Dim shocks As Variant shocks = Array(-0.02, -0.01, -0.005, 0, 0.005, 0.01, 0.02) Set ws = ThisWorkbook.Worksheets("Inputs") baseRate = ws.Range("IntRate").Value On Error Resume Next Application.DisplayAlerts = False ThisWorkbook.Worksheets("StressTest").Delete Application.DisplayAlerts = True On Error GoTo 0 Set stressWs = ThisWorkbook.Worksheets.Add(After:= _ ThisWorkbook.Worksheets(ThisWorkbook.Worksheets.Count)) stressWs.Name = "StressTest" stressWs.Range("B2").Value = "RATE STRESS TEST" stressWs.Range("B2").Font.Bold = True stressWs.Range("B2").Font.Size = 14 stressWs.Range("B4:E4").Value = Array("Shock (bps)", "New Rate", "Monthly Pmt", "Δ vs Base") For i = LBound(shocks) To UBound(shocks) Dim r As Integer r = 5 + i ws.Range("IntRate").Value = baseRate + shocks(i) Application.Calculate stressWs.Cells(r, 2).Value = shocks(i) * 10000 stressWs.Cells(r, 3).Value = ws.Range("IntRate").Value stressWs.Cells(r, 3).NumberFormat = "0.00%" stressWs.Cells(r, 4).Value = ws.Range("C15").Value stressWs.Cells(r, 4).NumberFormat = "$#,##0.00" stressWs.Cells(r, 5).Value = ws.Range("C15").Value - _ Evaluate("PMT(" & baseRate & "/12," & ws.Range("TermYrs").Value & _ "*12,-" & ws.Range("LoanAmt").Value & ")") stressWs.Cells(r, 5).NumberFormat = "$#,##0.00;($#,##0.00)" Next i ' Restore base ws.Range("IntRate").Value = baseRate Application.Calculate MsgBox "Stress test complete. See the StressTest sheet.", vbInformation End Sub ' Event handler — rebuild schedule when any input changes ' Install by pasting into the Inputs sheet module (right-click tab → View Code) Private Sub Worksheet_Change(ByVal Target As Range) Dim watched As Range Set watched = Me.Range("C5:C11") If Not Intersect(Target, watched) Is Nothing Then Application.EnableEvents = False Call AutoRefreshSchedule Application.EnableEvents = True End If End Sub
