Workbook

Sheet Cover
B2: THREE-STATEMENT FINANCIAL MODEL
B3: Income Statement · Balance Sheet · Cash Flow · Scenario Engine
B5: Integrated financial model linking the income statement, balance sheet, and cash flow statement, with a three-scenario driver (Base, Bull, Bear) selected via a CHOOSE-powered switch. Revenue cascades through margin assumptions; working-capital changes flow into cash; the balance sheet ties every year. A VBA macro runs a two-variable sensitivity table on revenue growth × EBITDA margin and writes the result to a dedicated sheet. Demonstrates the end-to-end modeling skillset expected of an FP&A or Financial Analyst role.

Sheet Assumptions
B2: SCENARIO DRIVERS
B4: Scenario | C4: 1 | D4: =CHOOSE(C4,"Base","Bull","Bear") -> Base | E4: Use 1=Base, 2=Bull, 3=Bear
B6: DRIVER GRID
B7: Driver | C7: Base | D7: Bull | E7: Bear | G7: Active (Scenario)
B8: Revenue Growth | C8: 0.08 | D8: 0.15 | E8: 0.02 | G8: =INDEX(C8:E8, 1, ScnID) -> 0.08
B9: Gross Margin | C9: 0.58 | D9: 0.62 | E9: 0.54 | G9: =INDEX(C9:E9, 1, ScnID) -> 0.58
B10: OpEx % of Revenue | C10: 0.32 | D10: 0.28 | E10: 0.36 | G10: =INDEX(C10:E10, 1, ScnID) -> 0.32
B11: Tax Rate | C11: 0.25 | D11: 0.25 | E11: 0.25 | G11: =INDEX(C11:E11, 1, ScnID) -> 0.25
B12: CapEx % of Revenue | C12: 0.05 | D12: 0.04 | E12: 0.07 | G12: =INDEX(C12:E12, 1, ScnID) -> 0.05
B13: D&A % of Revenue | C13: 0.04 | D13: 0.04 | E13: 0.04 | G13: =INDEX(C13:E13, 1, ScnID) -> 0.04
B14: Working Capital % Rev | C14: 0.12 | D14: 0.1 | E14: 0.15 | G14: =INDEX(C14:E14, 1, ScnID) -> 0.12
B15: Interest Rate on Debt | C15: 0.06 | D15: 0.05 | E15: 0.08 | G15: =INDEX(C15:E15, 1, ScnID) -> 0.06
B18: STARTING POSITION (FY2024 Actuals)
B19: Revenue | C19: 1200000
B20: Cash | C20: 180000
B21: Accounts Receivable | C21: 130000
B22: Inventory | C22: 95000
B23: PP&E (net) | C23: 650000
B24: Accounts Payable | C24: 85000
B25: Debt | C25: 450000
B26: Equity | C26: 520000

Sheet Income_Statement
B2: INCOME STATEMENT ($)
C4: FY2024 | D4: FY2025 | E4: FY2026 | F4: FY2027 | G4: FY2028
B5: Revenue | C5: =RevFY24 -> 1200000 | D5: =C5*(1+RevGrowth) -> 1296000 | E5: =D5*(1+RevGrowth) -> 1399680 | F5: =E5*(1+RevGrowth) -> 1511654.4 | G5: =F5*(1+RevGrowth) -> 1632586.8
B6: COGS | C6: =-C5*(1-GrossMargin) -> -504000 | D6: =-D5*(1-GrossMargin) -> -544320 | E6: =-E5*(1-GrossMargin) -> -587865.6 | F6: =-F5*(1-GrossMargin) -> -634894.85 | G6: =-G5*(1-GrossMargin) -> -685686.44
B7: Gross Profit | C7: =C5+C6 -> 696000 | D7: =D5+D6 -> 751680 | E7: =E5+E6 -> 811814.4 | F7: =F5+F6 -> 876759.55 | G7: =G5+G6 -> 946900.32
B8: Operating Expenses | C8: =-C5*OpExPct -> -384000 | D8: =-D5*OpExPct -> -414720 | E8: =-E5*OpExPct -> -447897.6 | F8: =-F5*OpExPct -> -483729.41 | G8: =-G5*OpExPct -> -522427.76
B9: EBITDA | C9: =C7+C8 -> 312000 | D9: =D7+D8 -> 336960 | E9: =E7+E8 -> 363916.8 | F9: =F7+F8 -> 393030.14 | G9: =G7+G8 -> 424472.56
B10: Depreciation & Amortization | C10: =-C5*DAPct -> -48000 | D10: =-D5*DAPct -> -51840 | E10: =-E5*DAPct -> -55987.2 | F10: =-F5*DAPct -> -60466.176 | G10: =-G5*DAPct -> -65303.47
B11: EBIT | C11: =C9+C10 -> 264000 | D11: =D9+D10 -> 285120 | E11: =E9+E10 -> 307929.6 | F11: =F9+F10 -> 332563.97 | G11: =G9+G10 -> 359169.09
B12: Interest Expense | C12: =-DebtFY24*IntRateDebt -> -27000 | D12: =-Balance_Sheet!C14*IntRateDebt -> -27000 | E12: =-Balance_Sheet!D14*IntRateDebt -> -27000 | F12: =-Balance_Sheet!E14*IntRateDebt -> -27000 | G12: =-Balance_Sheet!F14*IntRateDebt -> -27000
B13: EBT | C13: =C11+C12 -> 237000 | D13: =D11+D12 -> 258120 | E13: =E11+E12 -> 280929.6 | F13: =F11+F12 -> 305563.97 | G13: =G11+G12 -> 332169.09
B14: Taxes | C14: =-MAX(0,C13)*TaxRate -> -59250 | D14: =-MAX(0,D13)*TaxRate -> -64530 | E14: =-MAX(0,E13)*TaxRate -> -70232.4 | F14: =-MAX(0,F13)*TaxRate -> -76390.992 | G14: =-MAX(0,G13)*TaxRate -> -83042.271
B15: Net Income | C15: =C13+C14 -> 177750 | D15: =D13+D14 -> 193590 | E15: =E13+E14 -> 210697.2 | F15: =F13+F14 -> 229172.98 | G15: =G13+G14 -> 249126.81

Sheet Balance_Sheet
B2: BALANCE SHEET ($)
C4: FY2024 | D4: FY2025 | E4: FY2026 | F4: FY2027 | G4: FY2028
B5: ASSETS
B6: Cash | C6: =CashFY24 -> 180000 | D6: =C6+Cash_Flow!D12 -> 345110 | E6: =D6+Cash_Flow!E12 -> 529368.8 | F6: =E6+Cash_Flow!F12 -> 729988.3 | G6: =F6+Cash_Flow!G12 -> 948277.37
B7: Accounts Receivable | C7: =ARFY24 -> 130000 | D7: =Income_Statement!D5*0.11 -> 142560 | E7: =Income_Statement!E5*0.11 -> 153964.8 | F7: =Income_Statement!F5*0.11 -> 166281.98 | G7: =Income_Statement!G5*0.11 -> 179584.54
B8: Inventory | C8: =InvFY24 -> 95000 | D8: =Income_Statement!D5*0.08 -> 103680 | E8: =Income_Statement!E5*0.08 -> 111974.4 | F8: =Income_Statement!F5*0.08 -> 120932.35 | G8: =Income_Statement!G5*0.08 -> 130606.94
B9: Total Current Assets | C9: =SUM(C6:C8) -> 405000 | D9: =SUM(D6:D8) -> 591350 | E9: =SUM(E6:E8) -> 795308 | F9: =SUM(F6:F8) -> 1017202.6 | G9: =SUM(G6:G8) -> 1258468.9
B10: PP&E (Net) | C10: =PPEFY24 -> 650000 | D10: =C10+Income_Statement!D5*CapExPct+Income_Statement!D10 -> 662960 | E10: =D10+Income_Statement!E5*CapExPct+Income_Statement!E10 -> 676956.8 | F10: =E10+Income_Statement!F5*CapExPct+Income_Statement!F10 -> 692073.34 | G10: =F10+Income_Statement!G5*CapExPct+Income_Statement!G10 -> 708399.21
B11: Total Assets | C11: =C9+C10 -> 1055000 | D11: =D9+D10 -> 1254310 | E11: =E9+E10 -> 1472264.8 | F11: =F9+F10 -> 1709276 | G11: =G9+G10 -> 1966868.1
B12: LIABILITIES & EQUITY
B13: Accounts Payable | C13: =APFY24 -> 85000 | D13: =Income_Statement!D5*0.07 -> 90720 | E13: =Income_Statement!E5*0.07 -> 97977.6 | F13: =Income_Statement!F5*0.07 -> 105815.81 | G13: =Income_Statement!G5*0.07 -> 114281.07
B14: Debt | C14: =DebtFY24 -> 450000 | D14: =C14 -> 450000 | E14: =D14 -> 450000 | F14: =E14 -> 450000 | G14: =F14 -> 450000
B15: Total Liabilities | C15: =C13+C14 -> 535000 | D15: =D13+D14 -> 540720 | E15: =E13+E14 -> 547977.6 | F15: =F13+F14 -> 555815.81 | G15: =G13+G14 -> 564281.07
B16: Equity | C16: =EquityFY24 -> 520000 | D16: =C16+Income_Statement!D15 -> 713590 | E16: =D16+Income_Statement!E15 -> 924287.2 | F16: =E16+Income_Statement!F15 -> 1153460.2 | G16: =F16+Income_Statement!G15 -> 1402587
B17: Total L + E | C17: =C15+C16 -> 1055000 | D17: =D15+D16 -> 1254310 | E17: =E15+E16 -> 1472264.8 | F17: =F15+F16 -> 1709276 | G17: =G15+G16 -> 1966868.1
B18: Check (A = L+E) | C18: =C11-C17 -> 0 | D18: =D11-D17 -> 0 | E18: =E11-E17 -> 0 | F18: =F11-F17 -> 0 | G18: =G11-G17 -> 0

Sheet Cash_Flow
B2: CASH FLOW STATEMENT ($)
C4: FY2024 | D4: FY2025 | E4: FY2026 | F4: FY2027 | G4: FY2028
B5: Net Income | D5: =Income_Statement!D15 -> 193590 | E5: =Income_Statement!E15 -> 210697.2 | F5: =Income_Statement!F15 -> 229172.98 | G5: =Income_Statement!G15 -> 249126.81
B6: + D&A | D6: =-Income_Statement!D10 -> 51840 | E6: =-Income_Statement!E10 -> 55987.2 | F6: =-Income_Statement!F10 -> 60466.176 | G6: =-Income_Statement!G10 -> 65303.47
B7: - Increase in AR | D7: =-(Balance_Sheet!D7-Balance_Sheet!C7) -> -12560 | E7: =-(Balance_Sheet!E7-Balance_Sheet!D7) -> -11404.8 | F7: =-(Balance_Sheet!F7-Balance_Sheet!E7) -> -12317.184 | G7: =-(Balance_Sheet!G7-Balance_Sheet!F7) -> -13302.559
B8: - Increase in Inventory | D8: =-(Balance_Sheet!D8-Balance_Sheet!C8) -> -8680 | E8: =-(Balance_Sheet!E8-Balance_Sheet!D8) -> -8294.4 | F8: =-(Balance_Sheet!F8-Balance_Sheet!E8) -> -8957.952 | G8: =-(Balance_Sheet!G8-Balance_Sheet!F8) -> -9674.5882
B9: + Increase in AP | D9: =Balance_Sheet!D13-Balance_Sheet!C13 -> 5720 | E9: =Balance_Sheet!E13-Balance_Sheet!D13 -> 7257.6 | F9: =Balance_Sheet!F13-Balance_Sheet!E13 -> 7838.208 | G9: =Balance_Sheet!G13-Balance_Sheet!F13 -> 8465.2646
B10: Cash from Operations | D10: =SUM(D5:D9) -> 229910 | E10: =SUM(E5:E9) -> 254242.8 | F10: =SUM(F5:F9) -> 276202.22 | G10: =SUM(G5:G9) -> 299918.4
B11: - CapEx | D11: =-Income_Statement!D5*CapExPct -> -64800 | E11: =-Income_Statement!E5*CapExPct -> -69984 | F11: =-Income_Statement!F5*CapExPct -> -75582.72 | G11: =-Income_Statement!G5*CapExPct -> -81629.338
B12: Total Change in Cash | D12: =D10+D11 -> 165110 | E12: =E10+E11 -> 184258.8 | F12: =F10+F11 -> 200619.5 | G12: =G10+G11 -> 218289.06

Sheet Dashboard
B2: KPI DASHBOARD
B3: =CONCATENATE("Active Scenario: ", Assumptions!D4) -> Active Scenario: Base
C5: FY2024 | D5: FY2025 | E5: FY2026 | F5: FY2027 | G5: FY2028
B6: Revenue | C6: =Income_Statement!C5 -> 1200000 | D6: =Income_Statement!D5 -> 1296000 | E6: =Income_Statement!E5 -> 1399680 | F6: =Income_Statement!F5 -> 1511654.4 | G6: =Income_Statement!G5 -> 1632586.8
B7: Revenue Growth % | D7: =IFERROR(Income_Statement!D5/Income_Statement!C5-1,0) -> 0.08 | E7: =IFERROR(Income_Statement!E5/Income_Statement!D5-1,0) -> 0.08 | F7: =IFERROR(Income_Statement!F5/Income_Statement!E5-1,0) -> 0.08 | G7: =IFERROR(Income_Statement!G5/Income_Statement!F5-1,0) -> 0.08
B8: Gross Margin | C8: =Income_Statement!C7/Income_Statement!C5 -> 0.58 | D8: =Income_Statement!D7/Income_Statement!D5 -> 0.58 | E8: =Income_Statement!E7/Income_Statement!E5 -> 0.58 | F8: =Income_Statement!F7/Income_Statement!F5 -> 0.58 | G8: =Income_Statement!G7/Income_Statement!G5 -> 0.58
B9: EBITDA Margin | C9: =Income_Statement!C9/Income_Statement!C5 -> 0.26 | D9: =Income_Statement!D9/Income_Statement!D5 -> 0.26 | E9: =Income_Statement!E9/Income_Statement!E5 -> 0.26 | F9: =Income_Statement!F9/Income_Statement!F5 -> 0.26 | G9: =Income_Statement!G9/Income_Statement!G5 -> 0.26
B10: Net Margin | C10: =Income_Statement!C15/Income_Statement!C5 -> 0.148125 | D10: =Income_Statement!D15/Income_Statement!D5 -> 0.149375 | E10: =Income_Statement!E15/Income_Statement!E5 -> 0.15053241 | F10: =Income_Statement!F15/Income_Statement!F5 -> 0.15160408 | G10: =Income_Statement!G15/Income_Statement!G5 -> 0.15259637
B11: Current Ratio | C11: =Balance_Sheet!C9/Balance_Sheet!C13 -> 4.7647059 | D11: =Balance_Sheet!D9/Balance_Sheet!D13 -> 6.5184083 | E11: =Balance_Sheet!E9/Balance_Sheet!E13 -> 8.1172431 | F11: =Balance_Sheet!F9/Balance_Sheet!F13 -> 9.6129554 | G11: =Balance_Sheet!G9/Balance_Sheet!G13 -> 11.01205
B12: Debt / Equity | C12: =Balance_Sheet!C14/Balance_Sheet!C16 -> 0.86538462 | D12: =Balance_Sheet!D14/Balance_Sheet!D16 -> 0.63061422 | E12: =Balance_Sheet!E14/Balance_Sheet!E16 -> 0.48686166 | F12: =Balance_Sheet!F14/Balance_Sheet!F16 -> 0.3901305 | G12: =Balance_Sheet!G14/Balance_Sheet!G16 -> 0.32083572
B13: ROE | C13: =IFERROR(Income_Statement!C15/Balance_Sheet!C16,0) -> 0.34182692 | D13: =IFERROR(Income_Statement!D15/Balance_Sheet!D16,0) -> 0.27129024 | E13: =IFERROR(Income_Statement!E15/Balance_Sheet!E16,0) -> 0.22795642 | F13: =IFERROR(Income_Statement!F15/Balance_Sheet!F16,0) -> 0.19868304 | G13: =IFERROR(Income_Statement!G15/Balance_Sheet!G16,0) -> 0.17761951

Sheet VBA_Code
B2: VBA MACROS — Scenario Switch & Sensitivity
B3: Import ScenarioMacros.bas via Alt+F11 → File → Import File.
B5: Option Explicit ' ============================================================ ' ScenarioMacros.bas — Kartik Joshi ' Three-statement model: scenario switcher + sensitivity table ' ============================================================ Public Sub SwitchScenario(ByVal scnID As Integer) If scnID < 1 Or scnID > 3 Then MsgBox "Scenario ID must be 1 (Base), 2 (Bull), or 3 (Bear).", vbExclamation Exit Sub End If ThisWorkbook.Worksheets("Assumptions").Range("ScnID").Value = scnID Application.Calculate End Sub Public Sub RunBase(): SwitchScenario 1: End Sub Public Sub RunBull(): SwitchScenario 2: End Sub Public Sub RunBear(): SwitchScenario 3: End Sub ' Two-variable sensitivity table: ' Rows = Revenue growth (-4% to +20% in 2% steps) ' Cols = Gross margin (50% to 66% in 2% steps) ' Output = FY2028 EBITDA Public Sub BuildSensitivityTable() Dim ws As Worksheet, asn As Worksheet, origGrowth As Double, origMargin As Double Dim i As Integer, j As Integer Dim growths As Variant, margins As Variant Set asn = ThisWorkbook.Worksheets("Assumptions") origGrowth = asn.Range("RevGrowth").Value origMargin = asn.Range("GrossMargin").Value ' Overwrite the active column directly (col G rows 8 and 9) growths = Array(-0.04, -0.02, 0#, 0.02, 0.04, 0.06, 0.08, 0.1, 0.12, 0.14, 0.16, 0.18, 0.2) margins = Array(0.5, 0.52, 0.54, 0.56, 0.58, 0.6, 0.62, 0.64, 0.66) On Error Resume Next Application.DisplayAlerts = False ThisWorkbook.Worksheets("Sensitivity").Delete Application.DisplayAlerts = True On Error GoTo 0 Set ws = ThisWorkbook.Worksheets.Add(After:= _ ThisWorkbook.Worksheets(ThisWorkbook.Worksheets.Count)) ws.Name = "Sensitivity" ws.Range("B2").Value = "FY2028 EBITDA — Revenue Growth (rows) vs Gross Margin (cols)" ws.Range("B2").Font.Bold = True ws.Range("B2").Font.Size = 14 For j = LBound(margins) To UBound(margins) ws.Cells(4, 3 + j).Value = margins(j) ws.Cells(4, 3 + j).NumberFormat = "0.0%" ws.Cells(4, 3 + j).Font.Bold = True Next j For i = LBound(growths) To UBound(growths) ws.Cells(5 + i, 2).Value = growths(i) ws.Cells(5 + i, 2).NumberFormat = "0.0%" ws.Cells(5 + i, 2).Font.Bold = True For j = LBound(margins) To UBound(margins) asn.Range("RevGrowth").Value = growths(i) asn.Range("GrossMargin").Value = margins(j) Application.Calculate ws.Cells(5 + i, 3 + j).Value = _ ThisWorkbook.Worksheets("Income_Statement").Range("G9").Value ws.Cells(5 + i, 3 + j).NumberFormat = "$#,##0" Next j Next i asn.Range("RevGrowth").Value = origGrowth asn.Range("GrossMargin").Value = origMargin Application.Calculate MsgBox "Sensitivity table built. See the Sensitivity sheet.", vbInformation End Sub
