Workbook

Sheet Cover
B2: FP&A BUDGET SIMULATOR
B3: Budget vs Actual · Variance Analysis · Monte Carlo Forecast
B5: A complete FP&A workflow: monthly budget vs actual across five business units, SUMIFS-driven variance rollup, a two-way INDEX/MATCH lookup by month × unit, and a VBA-powered Monte Carlo simulation that runs 1,000 trials on revenue growth (sampled from a triangular distribution: -2% min, 8% mode, 18% max) to produce a forecast distribution with P10/P50/P90 percentiles. Demonstrates the core toolkit expected in a Senior Financial Analyst or FP&A role.

Sheet Data
B2: BUDGET vs ACTUAL — LINE ITEMS
B4: Month | C4: Month # | D4: Business Unit | E4: Line Item | F4: Budget ($) | G4: Actual ($)
B5: Jan | C5: 1 | D5: Retail Banking | E5: Revenue | F5: 121466 | G5: 141240
B6: Jan | C6: 1 | D6: Retail Banking | E6: Salaries | F6: 63524 | G6: 65723
B7: Jan | C7: 1 | D7: Retail Banking | E7: Technology | F7: 10311 | G7: 12906
B8: Jan | C8: 1 | D8: Retail Banking | E8: Marketing | F8: 6925 | G8: 6620
B9: Jan | C9: 1 | D9: Retail Banking | E9: Facilities | F9: 7484 | G9: 7790
B10: Jan | C10: 1 | D10: Retail Banking | E10: Travel | F10: 3454 | G10: 1869
B11: Jan | C11: 1 | D11: Retail Banking | E11: Professional Fees | F11: 7862 | G11: 8133
B12: Jan | C12: 1 | D12: Corporate Finance | E12: Revenue | F12: 143658 | G12: 126409
B13: Jan | C13: 1 | D13: Corporate Finance | E13: Salaries | F13: 80865 | G13: 77443
B14: Jan | C14: 1 | D14: Corporate Finance | E14: Technology | F14: 18948 | G14: 16448
B15: Jan | C15: 1 | D15: Corporate Finance | E15: Marketing | F15: 10242 | G15: 11690
B16: Jan | C16: 1 | D16: Corporate Finance | E16: Facilities | F16: 12580 | G16: 13143
... B424: Dec | C424: 12 | D424: Operations | E424: Professional Fees | F424: 4996 | G424: 4288

Sheet Summary
B2: MONTHLY BUDGET vs ACTUAL — BY BUSINESS UNIT
B4: Business Unit | C4: Jan | D4: Feb | E4: Mar | F4: Apr | G4: May | H4: Jun | I4: Jul | J4: Aug | K4: Sep | L4: Oct | M4: Nov | N4: Dec | O4: FY Total
B5: Retail Banking | C5: =IFERROR((SUMIFS(Data!$G$5:$G$424, Data!$B$5:$B$424, "Jan", Data!$D$5:$D$424, "Retail Banking")-SUMIFS(Data!$F$5:$F$424, Data!$B$5:$B$424, "Jan", Data!$D$5:$D$424, "Retail Banking"))/SUMIFS(Data!$F$5:$F$424, Data!$B$5:$B$424, "Jan", Data!$D$5:$D$424, "Retail Banking"), 0) -> 0.10521387 | D5: =IFERROR((SUMIFS(Data!$G$5:$G$424, Data!$B$5:$B$424, "Feb", Data!$D$5:$D$424, "Retail Banking")-SUMIFS(Data!$F$5:$F$424, Data!$B$5:$B$424, "Feb", Data!$D$5:$D$424, "Retail Banking"))/SUMIFS(Data!$F$5:$F$424, Data!$B$5:$B$424, "Feb", Data!$D$5:$D$424, "Retail Banking"), 0) -> -0.040422606 | E5: =IFERROR((SUMIFS(Data!$G$5:$G$424, Data!$B$5:$B$424, "Mar", Data!$D$5:$D$424, "Retail Banking")-SUMIFS(Data!$F$5:$F$424, Data!$B$5:$B$424, "Mar", Data!$D$5:$D$424, "Retail Banking"))/SUMIFS(Data!$F$5:$F$424, Data!$B$5:$B$424, "Mar", Data!$D$5:$D$424, "Retail Banking"), 0) -> 0.11789561 | F5: =IFERROR((SUMIFS(Data!$G$5:$G$424, Data!$B$5:$B$424, "Apr", Data!$D$5:$D$424, "Retail Banking")-SUMIFS(Data!$F$5:$F$424, Data!$B$5:$B$424, "Apr", Data!$D$5:$D$424, "Retail Banking"))/SUMIFS(Data!$F$5:$F$424, Data!$B$5:$B$424, "Apr", Data!$D$5:$D$424, "Retail Banking"), 0) -> 0.057437185 | G5: =IFERROR((SUMIFS(Data!$G$5:$G$424, Data!$B$5:$B$424, "May", Data!$D$5:$D$424, "Retail Banking")-SUMIFS(Data!$F$5:$F$424, Data!$B$5:$B$424, "May", Data!$D$5:$D$424, "Retail Banking"))/SUMIFS(Data!$F$5:$F$424, Data!$B$5:$B$424, "May", Data!$D$5:$D$424, "Retail Banking"), 0) -> 0.0085640202 | H5: =IFERROR((SUMIFS(Data!$G$5:$G$424, Data!$B$5:$B$424, "Jun", Data!$D$5:$D$424, "Retail Banking")-SUMIFS(Data!$F$5:$F$424, Data!$B$5:$B$424, "Jun", Data!$D$5:$D$424, "Retail Banking"))/SUMIFS(Data!$F$5:$F$424, Data!$B$5:$B$424, "Jun", Data!$D$5:$D$424, "Retail Banking"), 0) -> -0.010646425 | I5: =IFERROR((SUMIFS(Data!$G$5:$G$424, Data!$B$5:$B$424, "Jul", Data!$D$5:$D$424, "Retail Banking")-SUMIFS(Data!$F$5:$F$424, Data!$B$5:$B$424, "Jul", Data!$D$5:$D$424, "Retail Banking"))/SUMIFS(Data!$F$5:$F$424, Data!$B$5:$B$424, "Jul", Data!$D$5:$D$424, "Retail Banking"), 0) -> -0.051370547 | J5: =IFERROR((SUMIFS(Data!$G$5:$G$424, Data!$B$5:$B$424, "Aug", Data!$D$5:$D$424, "Retail Banking")-SUMIFS(Data!$F$5:$F$424, Data!$B$5:$B$424, "Aug", Data!$D$5:$D$424, "Retail Banking"))/SUMIFS(Data!$F$5:$F$424, Data!$B$5:$B$424, "Aug", Data!$D$5:$D$424, "Retail Banking"), 0) -> -0.059260077 | K5: =IFERROR((SUMIFS(Data!$G$5:$G$424, Data!$B$5:$B$424, "Sep", Data!$D$5:$D$424, "Retail Banking")-SUMIFS(Data!$F$5:$F$424, Data!$B$5:$B$424, "Sep", Data!$D$5:$D$424, "Retail Banking"))/SUMIFS(Data!$F$5:$F$424, Data!$B$5:$B$424, "Sep", Data!$D$5:$D$424, "Retail Banking"), 0) -> 0.027035669 | L5: =IFERROR((SUMIFS(Data!$G$5:$G$424, Data!$B$5:$B$424, "Oct", Data!$D$5:$D$424, "Retail Banking")-SUMIFS(Data!$F$5:$F$424, Data!$B$5:$B$424, "Oct", Data!$D$5:$D$424, "Retail Banking"))/SUMIFS(Data!$F$5:$F$424, Data!$B$5:$B$424, "Oct", Data!$D$5:$D$424, "Retail Banking"), 0) -> -0.036528631 | M5: =IFERROR((SUMIFS(Data!$G$5:$G$424, Data!$B$5:$B$424, "Nov", Data!$D$5:$D$424, "Retail Banking")-SUMIFS(Data!$F$5:$F$424, Data!$B$5:$B$424, "Nov", Data!$D$5:$D$424, "Retail Banking"))/SUMIFS(Data!$F$5:$F$424, Data!$B$5:$B$424, "Nov", Data!$D$5:$D$424, "Retail Banking"), 0) -> 0.034280311 | N5: =IFERROR((SUMIFS(Data!$G$5:$G$424, Data!$B$5:$B$424, "Dec", Data!$D$5:$D$424, "Retail Banking")-SUMIFS(Data!$F$5:$F$424, Data!$B$5:$B$424, "Dec", Data!$D$5:$D$424, "Retail Banking"))/SUMIFS(Data!$F$5:$F$424, Data!$B$5:$B$424, "Dec", Data!$D$5:$D$424, "Retail Banking"), 0) -> -0.027498633 | O5: =IFERROR((SUMIFS(Data!$G$5:$G$424, Data!$D$5:$D$424, "Retail Banking")-SUMIFS(Data!$F$5:$F$424, Data!$D$5:$D$424, "Retail Banking"))/SUMIFS(Data!$F$5:$F$424, Data!$D$5:$D$424, "Retail Banking"), 0) -> 0.010677803
B6: Corporate Finance | C6: =IFERROR((SUMIFS(Data!$G$5:$G$424, Data!$B$5:$B$424, "Jan", Data!$D$5:$D$424, "Corporate Finance")-SUMIFS(Data!$F$5:$F$424, Data!$B$5:$B$424, "Jan", Data!$D$5:$D$424, "Corporate Finance"))/SUMIFS(Data!$F$5:$F$424, Data!$B$5:$B$424, "Jan", Data!$D$5:$D$424, "Corporate Finance"), 0) -> -0.063900902 | D6: =IFERROR((SUMIFS(Data!$G$5:$G$424, Data!$B$5:$B$424, "Feb", Data!$D$5:$D$424, "Corporate Finance")-SUMIFS(Data!$F$5:$F$424, Data!$B$5:$B$424, "Feb", Data!$D$5:$D$424, "Corporate Finance"))/SUMIFS(Data!$F$5:$F$424, Data!$B$5:$B$424, "Feb", Data!$D$5:$D$424, "Corporate Finance"), 0) -> 0.083069952 | E6: =IFERROR((SUMIFS(Data!$G$5:$G$424, Data!$B$5:$B$424, "Mar", Data!$D$5:$D$424, "Corporate Finance")-SUMIFS(Data!$F$5:$F$424, Data!$B$5:$B$424, "Mar", Data!$D$5:$D$424, "Corporate Finance"))/SUMIFS(Data!$F$5:$F$424, Data!$B$5:$B$424, "Mar", Data!$D$5:$D$424, "Corporate Finance"), 0) -> 0.06718618 | F6: =IFERROR((SUMIFS(Data!$G$5:$G$424, Data!$B$5:$B$424, "Apr", Data!$D$5:$D$424, "Corporate Finance")-SUMIFS(Data!$F$5:$F$424, Data!$B$5:$B$424, "Apr", Data!$D$5:$D$424, "Corporate Finance"))/SUMIFS(Data!$F$5:$F$424, Data!$B$5:$B$424, "Apr", Data!$D$5:$D$424, "Corporate Finance"), 0) -> 0.1248513 | G6: =IFERROR((SUMIFS(Data!$G$5:$G$424, Data!$B$5:$B$424, "May", Data!$D$5:$D$424, "Corporate Finance")-SUMIFS(Data!$F$5:$F$424, Data!$B$5:$B$424, "May", Data!$D$5:$D$424, "Corporate Finance"))/SUMIFS(Data!$F$5:$F$424, Data!$B$5:$B$424, "May", Data!$D$5:$D$424, "Corporate Finance"), 0) -> 0.10920446 | H6: =IFERROR((SUMIFS(Data!$G$5:$G$424, Data!$B$5:$B$424, "Jun", Data!$D$5:$D$424, "Corporate Finance")-SUMIFS(Data!$F$5:$F$424, Data!$B$5:$B$424, "Jun", Data!$D$5:$D$424, "Corporate Finance"))/SUMIFS(Data!$F$5:$F$424, Data!$B$5:$B$424, "Jun", Data!$D$5:$D$424, "Corporate Finance"), 0) -> 0.098356983 | I6: =IFERROR((SUMIFS(Data!$G$5:$G$424, Data!$B$5:$B$424, "Jul", Data!$D$5:$D$424, "Corporate Finance")-SUMIFS(Data!$F$5:$F$424, Data!$B$5:$B$424, "Jul", Data!$D$5:$D$424, "Corporate Finance"))/SUMIFS(Data!$F$5:$F$424, Data!$B$5:$B$424, "Jul", Data!$D$5:$D$424, "Corporate Finance"), 0) -> 0.083780601 | J6: =IFERROR((SUMIFS(Data!$G$5:$G$424, Data!$B$5:$B$424, "Aug", Data!$D$5:$D$424, "Corporate Finance")-SUMIFS(Data!$F$5:$F$424, Data!$B$5:$B$424, "Aug", Data!$D$5:$D$424, "Corporate Finance"))/SUMIFS(Data!$F$5:$F$424, Data!$B$5:$B$424, "Aug", Data!$D$5:$D$424, "Corporate Finance"), 0) -> -0.084787738 | K6: =IFERROR((SUMIFS(Data!$G$5:$G$424, Data!$B$5:$B$424, "Sep", Data!$D$5:$D$424, "Corporate Finance")-SUMIFS(Data!$F$5:$F$424, Data!$B$5:$B$424, "Sep", Data!$D$5:$D$424, "Corporate Finance"))/SUMIFS(Data!$F$5:$F$424, Data!$B$5:$B$424, "Sep", Data!$D$5:$D$424, "Corporate Finance"), 0) -> 0.092149896 | L6: =IFERROR((SUMIFS(Data!$G$5:$G$424, Data!$B$5:$B$424, "Oct", Data!$D$5:$D$424, "Corporate Finance")-SUMIFS(Data!$F$5:$F$424, Data!$B$5:$B$424, "Oct", Data!$D$5:$D$424, "Corporate Finance"))/SUMIFS(Data!$F$5:$F$424, Data!$B$5:$B$424, "Oct", Data!$D$5:$D$424, "Corporate Finance"), 0) -> -0.027988215 | M6: =IFERROR((SUMIFS(Data!$G$5:$G$424, Data!$B$5:$B$424, "Nov", Data!$D$5:$D$424, "Corporate Finance")-SUMIFS(Data!$F$5:$F$424, Data!$B$5:$B$424, "Nov", Data!$D$5:$D$424, "Corporate Finance"))/SUMIFS(Data!$F$5:$F$424, Data!$B$5:$B$424, "Nov", Data!$D$5:$D$424, "Corporate Finance"), 0) -> -0.0086700898 | N6: =IFERROR((SUMIFS(Data!$G$5:$G$424, Data!$B$5:$B$424, "Dec", Data!$D$5:$D$424, "Corporate Finance")-SUMIFS(Data!$F$5:$F$424, Data!$B$5:$B$424, "Dec", Data!$D$5:$D$424, "Corporate Finance"))/SUMIFS(Data!$F$5:$F$424, Data!$B$5:$B$424, "Dec", Data!$D$5:$D$424, "Corporate Finance"), 0) -> 0.050689865 | O6: =IFERROR((SUMIFS(Data!$G$5:$G$424, Data!$D$5:$D$424, "Corporate Finance")-SUMIFS(Data!$F$5:$F$424, Data!$D$5:$D$424, "Corporate Finance"))/SUMIFS(Data!$F$5:$F$424, Data!$D$5:$D$424, "Corporate Finance"), 0) -> 0.042687782
B7: Wealth Management | C7: =IFERROR((SUMIFS(Data!$G$5:$G$424, Data!$B$5:$B$424, "Jan", Data!$D$5:$D$424, "Wealth Management")-SUMIFS(Data!$F$5:$F$424, Data!$B$5:$B$424, "Jan", Data!$D$5:$D$424, "Wealth Management"))/SUMIFS(Data!$F$5:$F$424, Data!$B$5:$B$424, "Jan", Data!$D$5:$D$424, "Wealth Management"), 0) -> 0.015841933 | D7: =IFERROR((SUMIFS(Data!$G$5:$G$424, Data!$B$5:$B$424, "Feb", Data!$D$5:$D$424, "Wealth Management")-SUMIFS(Data!$F$5:$F$424, Data!$B$5:$B$424, "Feb", Data!$D$5:$D$424, "Wealth Management"))/SUMIFS(Data!$F$5:$F$424, Data!$B$5:$B$424, "Feb", Data!$D$5:$D$424, "Wealth Management"), 0) -> -0.10096529 | E7: =IFERROR((SUMIFS(Data!$G$5:$G$424, Data!$B$5:$B$424, "Mar", Data!$D$5:$D$424, "Wealth Management")-SUMIFS(Data!$F$5:$F$424, Data!$B$5:$B$424, "Mar", Data!$D$5:$D$424, "Wealth Management"))/SUMIFS(Data!$F$5:$F$424, Data!$B$5:$B$424, "Mar", Data!$D$5:$D$424, "Wealth Management"), 0) -> 0.029175152 | F7: =IFERROR((SUMIFS(Data!$G$5:$G$424, Data!$B$5:$B$424, "Apr", Data!$D$5:$D$424, "Wealth Management")-SUMIFS(Data!$F$5:$F$424, Data!$B$5:$B$424, "Apr", Data!$D$5:$D$424, "Wealth Management"))/SUMIFS(Data!$F$5:$F$424, Data!$B$5:$B$424, "Apr", Data!$D$5:$D$424, "Wealth Management"), 0) -> 0.12183179 | G7: =IFERROR((SUMIFS(Data!$G$5:$G$424, Data!$B$5:$B$424, "May", Data!$D$5:$D$424, "Wealth Management")-SUMIFS(Data!$F$5:$F$424, Data!$B$5:$B$424, "May", Data!$D$5:$D$424, "Wealth Management"))/SUMIFS(Data!$F$5:$F$424, Data!$B$5:$B$424, "May", Data!$D$5:$D$424, "Wealth Management"), 0) -> 0.045888814 | H7: =IFERROR((SUMIFS(Data!$G$5:$G$424, Data!$B$5:$B$424, "Jun", Data!$D$5:$D$424, "Wealth Management")-SUMIFS(Data!$F$5:$F$424, Data!$B$5:$B$424, "Jun", Data!$D$5:$D$424, "Wealth Management"))/SUMIFS(Data!$F$5:$F$424, Data!$B$5:$B$424, "Jun", Data!$D$5:$D$424, "Wealth Management"), 0) -> -0.064180237 | I7: =IFERROR((SUMIFS(Data!$G$5:$G$424, Data!$B$5:$B$424, "Jul", Data!$D$5:$D$424, "Wealth Management")-SUMIFS(Data!$F$5:$F$424, Data!$B$5:$B$424, "Jul", Data!$D$5:$D$424, "Wealth Management"))/SUMIFS(Data!$F$5:$F$424, Data!$B$5:$B$424, "Jul", Data!$D$5:$D$424, "Wealth Management"), 0) -> 0.10252933 | J7: =IFERROR((SUMIFS(Data!$G$5:$G$424, Data!$B$5:$B$424, "Aug", Data!$D$5:$D$424, "Wealth Management")-SUMIFS(Data!$F$5:$F$424, Data!$B$5:$B$424, "Aug", Data!$D$5:$D$424, "Wealth Management"))/SUMIFS(Data!$F$5:$F$424, Data!$B$5:$B$424, "Aug", Data!$D$5:$D$424, "Wealth Management"), 0) -> -0.0052577499 | K7: =IFERROR((SUMIFS(Data!$G$5:$G$424, Data!$B$5:$B$424, "Sep", Data!$D$5:$D$424, "Wealth Management")-SUMIFS(Data!$F$5:$F$424, Data!$B$5:$B$424, "Sep", Data!$D$5:$D$424, "Wealth Management"))/SUMIFS(Data!$F$5:$F$424, Data!$B$5:$B$424, "Sep", Data!$D$5:$D$424, "Wealth Management"), 0) -> 0.03450092 | L7: =IFERROR((SUMIFS(Data!$G$5:$G$424, Data!$B$5:$B$424, "Oct", Data!$D$5:$D$424, "Wealth Management")-SUMIFS(Data!$F$5:$F$424, Data!$B$5:$B$424, "Oct", Data!$D$5:$D$424, "Wealth Management"))/SUMIFS(Data!$F$5:$F$424, Data!$B$5:$B$424, "Oct", Data!$D$5:$D$424, "Wealth Management"), 0) -> 0.090798677 | M7: =IFERROR((SUMIFS(Data!$G$5:$G$424, Data!$B$5:$B$424, "Nov", Data!$D$5:$D$424, "Wealth Management")-SUMIFS(Data!$F$5:$F$424, Data!$B$5:$B$424, "Nov", Data!$D$5:$D$424, "Wealth Management"))/SUMIFS(Data!$F$5:$F$424, Data!$B$5:$B$424, "Nov", Data!$D$5:$D$424, "Wealth Management"), 0) -> -0.020213289 | N7: =IFERROR((SUMIFS(Data!$G$5:$G$424, Data!$B$5:$B$424, "Dec", Data!$D$5:$D$424, "Wealth Management")-SUMIFS(Data!$F$5:$F$424, Data!$B$5:$B$424, "Dec", Data!$D$5:$D$424, "Wealth Management"))/SUMIFS(Data!$F$5:$F$424, Data!$B$5:$B$424, "Dec", Data!$D$5:$D$424, "Wealth Management"), 0) -> 0.0086151111 | O7: =IFERROR((SUMIFS(Data!$G$5:$G$424, Data!$D$5:$D$424, "Wealth Management")-SUMIFS(Data!$F$5:$F$424, Data!$D$5:$D$424, "Wealth Management"))/SUMIFS(Data!$F$5:$F$424, Data!$D$5:$D$424, "Wealth Management"), 0) -> 0.020165634
B8: Compliance | C8: =IFERROR((SUMIFS(Data!$G$5:$G$424, Data!$B$5:$B$424, "Jan", Data!$D$5:$D$424, "Compliance")-SUMIFS(Data!$F$5:$F$424, Data!$B$5:$B$424, "Jan", Data!$D$5:$D$424, "Compliance"))/SUMIFS(Data!$F$5:$F$424, Data!$B$5:$B$424, "Jan", Data!$D$5:$D$424, "Compliance"), 0) -> 0.03533066 | D8: =IFERROR((SUMIFS(Data!$G$5:$G$424, Data!$B$5:$B$424, "Feb", Data!$D$5:$D$424, "Compliance")-SUMIFS(Data!$F$5:$F$424, Data!$B$5:$B$424, "Feb", Data!$D$5:$D$424, "Compliance"))/SUMIFS(Data!$F$5:$F$424, Data!$B$5:$B$424, "Feb", Data!$D$5:$D$424, "Compliance"), 0) -> 0.012857559 | E8: =IFERROR((SUMIFS(Data!$G$5:$G$424, Data!$B$5:$B$424, "Mar", Data!$D$5:$D$424, "Compliance")-SUMIFS(Data!$F$5:$F$424, Data!$B$5:$B$424, "Mar", Data!$D$5:$D$424, "Compliance"))/SUMIFS(Data!$F$5:$F$424, Data!$B$5:$B$424, "Mar", Data!$D$5:$D$424, "Compliance"), 0) -> 0.047212987 | F8: =IFERROR((SUMIFS(Data!$G$5:$G$424, Data!$B$5:$B$424, "Apr", Data!$D$5:$D$424, "Compliance")-SUMIFS(Data!$F$5:$F$424, Data!$B$5:$B$424, "Apr", Data!$D$5:$D$424, "Compliance"))/SUMIFS(Data!$F$5:$F$424, Data!$B$5:$B$424, "Apr", Data!$D$5:$D$424, "Compliance"), 0) -> 0.0035675625 | G8: =IFERROR((SUMIFS(Data!$G$5:$G$424, Data!$B$5:$B$424, "May", Data!$D$5:$D$424, "Compliance")-SUMIFS(Data!$F$5:$F$424, Data!$B$5:$B$424, "May", Data!$D$5:$D$424, "Compliance"))/SUMIFS(Data!$F$5:$F$424, Data!$B$5:$B$424, "May", Data!$D$5:$D$424, "Compliance"), 0) -> -0.038056005 | H8: =IFERROR((SUMIFS(Data!$G$5:$G$424, Data!$B$5:$B$424, "Jun", Data!$D$5:$D$424, "Compliance")-SUMIFS(Data!$F$5:$F$424, Data!$B$5:$B$424, "Jun", Data!$D$5:$D$424, "Compliance"))/SUMIFS(Data!$F$5:$F$424, Data!$B$5:$B$424, "Jun", Data!$D$5:$D$424, "Compliance"), 0) -> -0.050676752 | I8: =IFERROR((SUMIFS(Data!$G$5:$G$424, Data!$B$5:$B$424, "Jul", Data!$D$5:$D$424, "Compliance")-SUMIFS(Data!$F$5:$F$424, Data!$B$5:$B$424, "Jul", Data!$D$5:$D$424, "Compliance"))/SUMIFS(Data!$F$5:$F$424, Data!$B$5:$B$424, "Jul", Data!$D$5:$D$424, "Compliance"), 0) -> 0.11262908 | J8: =IFERROR((SUMIFS(Data!$G$5:$G$424, Data!$B$5:$B$424, "Aug", Data!$D$5:$D$424, "Compliance")-SUMIFS(Data!$F$5:$F$424, Data!$B$5:$B$424, "Aug", Data!$D$5:$D$424, "Compliance"))/SUMIFS(Data!$F$5:$F$424, Data!$B$5:$B$424, "Aug", Data!$D$5:$D$424, "Compliance"), 0) -> -0.032466936 | K8: =IFERROR((SUMIFS(Data!$G$5:$G$424, Data!$B$5:$B$424, "Sep", Data!$D$5:$D$424, "Compliance")-SUMIFS(Data!$F$5:$F$424, Data!$B$5:$B$424, "Sep", Data!$D$5:$D$424, "Compliance"))/SUMIFS(Data!$F$5:$F$424, Data!$B$5:$B$424, "Sep", Data!$D$5:$D$424, "Compliance"), 0) -> -0.064587091 | L8: =IFERROR((SUMIFS(Data!$G$5:$G$424, Data!$B$5:$B$424, "Oct", Data!$D$5:$D$424, "Compliance")-SUMIFS(Data!$F$5:$F$424, Data!$B$5:$B$424, "Oct", Data!$D$5:$D$424, "Compliance"))/SUMIFS(Data!$F$5:$F$424, Data!$B$5:$B$424, "Oct", Data!$D$5:$D$424, "Compliance"), 0) -> 0.068392941 | M8: =IFERROR((SUMIFS(Data!$G$5:$G$424, Data!$B$5:$B$424, "Nov", Data!$D$5:$D$424, "Compliance")-SUMIFS(Data!$F$5:$F$424, Data!$B$5:$B$424, "Nov", Data!$D$5:$D$424, "Compliance"))/SUMIFS(Data!$F$5:$F$424, Data!$B$5:$B$424, "Nov", Data!$D$5:$D$424, "Compliance"), 0) -> -0.0059720073 | N8: =IFERROR((SUMIFS(Data!$G$5:$G$424, Data!$B$5:$B$424, "Dec", Data!$D$5:$D$424, "Compliance")-SUMIFS(Data!$F$5:$F$424, Data!$B$5:$B$424, "Dec", Data!$D$5:$D$424, "Compliance"))/SUMIFS(Data!$F$5:$F$424, Data!$B$5:$B$424, "Dec", Data!$D$5:$D$424, "Compliance"), 0) -> -0.016456795 | O8: =IFERROR((SUMIFS(Data!$G$5:$G$424, Data!$D$5:$D$424, "Compliance")-SUMIFS(Data!$F$5:$F$424, Data!$D$5:$D$424, "Compliance"))/SUMIFS(Data!$F$5:$F$424, Data!$D$5:$D$424, "Compliance"), 0) -> 0.0078911711
B9: Operations | C9: =IFERROR((SUMIFS(Data!$G$5:$G$424, Data!$B$5:$B$424, "Jan", Data!$D$5:$D$424, "Operations")-SUMIFS(Data!$F$5:$F$424, Data!$B$5:$B$424, "Jan", Data!$D$5:$D$424, "Operations"))/SUMIFS(Data!$F$5:$F$424, Data!$B$5:$B$424, "Jan", Data!$D$5:$D$424, "Operations"), 0) -> 0.035829004 | D9: =IFERROR((SUMIFS(Data!$G$5:$G$424, Data!$B$5:$B$424, "Feb", Data!$D$5:$D$424, "Operations")-SUMIFS(Data!$F$5:$F$424, Data!$B$5:$B$424, "Feb", Data!$D$5:$D$424, "Operations"))/SUMIFS(Data!$F$5:$F$424, Data!$B$5:$B$424, "Feb", Data!$D$5:$D$424, "Operations"), 0) -> -0.040885126 | E9: =IFERROR((SUMIFS(Data!$G$5:$G$424, Data!$B$5:$B$424, "Mar", Data!$D$5:$D$424, "Operations")-SUMIFS(Data!$F$5:$F$424, Data!$B$5:$B$424, "Mar", Data!$D$5:$D$424, "Operations"))/SUMIFS(Data!$F$5:$F$424, Data!$B$5:$B$424, "Mar", Data!$D$5:$D$424, "Operations"), 0) -> 0.11766127 | F9: =IFERROR((SUMIFS(Data!$G$5:$G$424, Data!$B$5:$B$424, "Apr", Data!$D$5:$D$424, "Operations")-SUMIFS(Data!$F$5:$F$424, Data!$B$5:$B$424, "Apr", Data!$D$5:$D$424, "Operations"))/SUMIFS(Data!$F$5:$F$424, Data!$B$5:$B$424, "Apr", Data!$D$5:$D$424, "Operations"), 0) -> 0.11227479 | G9: =IFERROR((SUMIFS(Data!$G$5:$G$424, Data!$B$5:$B$424, "May", Data!$D$5:$D$424, "Operations")-SUMIFS(Data!$F$5:$F$424, Data!$B$5:$B$424, "May", Data!$D$5:$D$424, "Operations"))/SUMIFS(Data!$F$5:$F$424, Data!$B$5:$B$424, "May", Data!$D$5:$D$424, "Operations"), 0) -> 0.049152061 | H9: =IFERROR((SUMIFS(Data!$G$5:$G$424, Data!$B$5:$B$424, "Jun", Data!$D$5:$D$424, "Operations")-SUMIFS(Data!$F$5:$F$424, Data!$B$5:$B$424, "Jun", Data!$D$5:$D$424, "Operations"))/SUMIFS(Data!$F$5:$F$424, Data!$B$5:$B$424, "Jun", Data!$D$5:$D$424, "Operations"), 0) -> 0.091176052 | I9: =IFERROR((SUMIFS(Data!$G$5:$G$424, Data!$B$5:$B$424, "Jul", Data!$D$5:$D$424, "Operations")-SUMIFS(Data!$F$5:$F$424, Data!$B$5:$B$424, "Jul", Data!$D$5:$D$424, "Operations"))/SUMIFS(Data!$F$5:$F$424, Data!$B$5:$B$424, "Jul", Data!$D$5:$D$424, "Operations"), 0) -> -0.086591074 | J9: =IFERROR((SUMIFS(Data!$G$5:$G$424, Data!$B$5:$B$424, "Aug", Data!$D$5:$D$424, "Operations")-SUMIFS(Data!$F$5:$F$424, Data!$B$5:$B$424, "Aug", Data!$D$5:$D$424, "Operations"))/SUMIFS(Data!$F$5:$F$424, Data!$B$5:$B$424, "Aug", Data!$D$5:$D$424, "Operations"), 0) -> 0.097875398 | K9: =IFERROR((SUMIFS(Data!$G$5:$G$424, Data!$B$5:$B$424, "Sep", Data!$D$5:$D$424, "Operations")-SUMIFS(Data!$F$5:$F$424, Data!$B$5:$B$424, "Sep", Data!$D$5:$D$424, "Operations"))/SUMIFS(Data!$F$5:$F$424, Data!$B$5:$B$424, "Sep", Data!$D$5:$D$424, "Operations"), 0) -> -0.038206266 | L9: =IFERROR((SUMIFS(Data!$G$5:$G$424, Data!$B$5:$B$424, "Oct", Data!$D$5:$D$424, "Operations")-SUMIFS(Data!$F$5:$F$424, Data!$B$5:$B$424, "Oct", Data!$D$5:$D$424, "Operations"))/SUMIFS(Data!$F$5:$F$424, Data!$B$5:$B$424, "Oct", Data!$D$5:$D$424, "Operations"), 0) -> 0.096075627 | M9: =IFERROR((SUMIFS(Data!$G$5:$G$424, Data!$B$5:$B$424, "Nov", Data!$D$5:$D$424, "Operations")-SUMIFS(Data!$F$5:$F$424, Data!$B$5:$B$424, "Nov", Data!$D$5:$D$424, "Operations"))/SUMIFS(Data!$F$5:$F$424, Data!$B$5:$B$424, "Nov", Data!$D$5:$D$424, "Operations"), 0) -> -0.024146128 | N9: =IFERROR((SUMIFS(Data!$G$5:$G$424, Data!$B$5:$B$424, "Dec", Data!$D$5:$D$424, "Operations")-SUMIFS(Data!$F$5:$F$424, Data!$B$5:$B$424, "Dec", Data!$D$5:$D$424, "Operations"))/SUMIFS(Data!$F$5:$F$424, Data!$B$5:$B$424, "Dec", Data!$D$5:$D$424, "Operations"), 0) -> 0.066634844 | O9: =IFERROR((SUMIFS(Data!$G$5:$G$424, Data!$D$5:$D$424, "Operations")-SUMIFS(Data!$F$5:$F$424, Data!$D$5:$D$424, "Operations"))/SUMIFS(Data!$F$5:$F$424, Data!$D$5:$D$424, "Operations"), 0) -> 0.041448121
B12: TWO-WAY LOOKUP (INDEX/MATCH)
B14: Select Month | C14: Jun
B15: Select Business Unit | C15: Corporate Finance
B17: Variance % (lookup) | C17: =INDEX(C5:N9, MATCH(C15, B5:B9, 0), MATCH(C14, C4:N4, 0)) -> 0.098356983

Sheet MonteCarlo
B2: MONTE CARLO REVENUE FORECAST
B4: INPUTS
B5: Base Revenue ($) | C5: 5000000
B6: Min Growth Rate | C6: -0.02
B7: Mode Growth Rate | C7: 0.08
B8: Max Growth Rate | C8: 0.18
B9: Number of Trials | C9: 1000
B10: Forecast Horizon (yrs) | C10: 3
B13: RESULTS (populated by VBA macro)
B14: Percentile | C14: Forecast Revenue
B15: P10 (Bear) | C15: — run macro —
B16: P25 | C16: — run macro —
B17: P50 (Median) | C17: — run macro —
B18: P75 | C18: — run macro —
B19: P90 (Bull) | C19: — run macro —
B20: Mean | C20: — run macro —
B21: Std Dev | C21: — run macro —

Sheet VBA_Code
B2: VBA MACROS — Monte Carlo Simulator
B3: Import FPAMacros.bas via Alt+F11 → File → Import File.
B5: Option Explicit ' ============================================================ ' FPAMacros.bas — Kartik Joshi ' FP&A Budget Simulator — Monte Carlo revenue forecast ' Triangular distribution on annual growth rate ' ============================================================ Public Sub RunMonteCarlo() Dim mc As Worksheet, out As Worksheet Dim trials As Long, horizon As Long, i As Long, y As Long Dim baseRev As Double, minG As Double, modeG As Double, maxG As Double Dim rev As Double, u As Double, g As Double, Fc As Double Set mc = ThisWorkbook.Worksheets("MonteCarlo") baseRev = mc.Range("MC_BaseRev").Value minG = mc.Range("MC_MinG").Value modeG = mc.Range("MC_ModeG").Value maxG = mc.Range("MC_MaxG").Value trials = mc.Range("MC_Trials").Value horizon = mc.Range("MC_Horizon").Value ' Prepare output sheet On Error Resume Next Application.DisplayAlerts = False ThisWorkbook.Worksheets("MC_Results").Delete Application.DisplayAlerts = True On Error GoTo 0 Set out = ThisWorkbook.Worksheets.Add(After:= _ ThisWorkbook.Worksheets(ThisWorkbook.Worksheets.Count)) out.Name = "MC_Results" out.Range("A1").Value = "Trial" out.Range("B1").Value = "Forecast Revenue" out.Range("A1:B1").Font.Bold = True ' Triangular sampling using inverse CDF ' Fc = (mode - min)/(max - min) Fc = (modeG - minG) / (maxG - minG) Application.ScreenUpdating = False Randomize ReDim results(1 To trials) As Double For i = 1 To trials rev = baseRev For y = 1 To horizon u = Rnd() If u < Fc Then g = minG + Sqr(u * (maxG - minG) * (modeG - minG)) Else g = maxG - Sqr((1 - u) * (maxG - minG) * (maxG - modeG)) End If rev = rev * (1 + g) Next y results(i) = rev out.Cells(i + 1, 1).Value = i out.Cells(i + 1, 2).Value = rev Next i out.Columns("B").NumberFormat = "$#,##0" Application.ScreenUpdating = True ' Write percentiles back to MonteCarlo sheet mc.Range("C15").Value = WorksheetFunction.Percentile(results, 0.1) mc.Range("C16").Value = WorksheetFunction.Percentile(results, 0.25) mc.Range("C17").Value = WorksheetFunction.Percentile(results, 0.5) mc.Range("C18").Value = WorksheetFunction.Percentile(results, 0.75) mc.Range("C19").Value = WorksheetFunction.Percentile(results, 0.9) mc.Range("C20").Value = WorksheetFunction.Average(results) mc.Range("C21").Value = WorksheetFunction.StDev(results) mc.Range("C15:C21").NumberFormat = "$#,##0" mc.Range("C15:C21").Font.Color = RGB(0, 0, 0) mc.Range("C15:C21").Font.Bold = True mc.Range("C15:C21").Interior.Color = RGB(213, 245, 227) MsgBox trials & " Monte Carlo trials complete over " & horizon & "-year horizon.", vbInformation End Sub Public Sub ExportVarianceReport() Dim src As Worksheet, rep As Worksheet, i As Long, outRow As Long, threshold As Double Set src = ThisWorkbook.Worksheets("Data") threshold = 0.15 ' 15% variance threshold for exceptions On Error Resume Next Application.DisplayAlerts = False ThisWorkbook.Worksheets("Variance_Exceptions").Delete Application.DisplayAlerts = True On Error GoTo 0 Set rep = ThisWorkbook.Worksheets.Add(After:= _ ThisWorkbook.Worksheets(ThisWorkbook.Worksheets.Count)) rep.Name = "Variance_Exceptions" rep.Range("B2").Value = "VARIANCE EXCEPTIONS (> 15% over/under budget)" rep.Range("B2").Font.Bold = True rep.Range("B2").Font.Size = 14 Dim headers As Variant headers = Array("Month", "Business Unit", "Line Item", "Budget", "Actual", "Variance $", "Variance %") Dim j As Integer For j = LBound(headers) To UBound(headers) rep.Cells(4, 2 + j).Value = headers(j) rep.Cells(4, 2 + j).Font.Bold = True rep.Cells(4, 2 + j).Interior.Color = RGB(27, 42, 73) rep.Cells(4, 2 + j).Font.Color = RGB(255, 255, 255) Next j outRow = 5 Dim pct As Double For i = 5 To 424 If src.Cells(i, 6).Value > 0 Then pct = (src.Cells(i, 7).Value - src.Cells(i, 6).Value) / src.Cells(i, 6).Value If Abs(pct) > threshold Then rep.Cells(outRow, 2).Value = src.Cells(i, 2).Value rep.Cells(outRow, 3).Value = src.Cells(i, 4).Value rep.Cells(outRow, 4).Value = src.Cells(i, 5).Value rep.Cells(outRow, 5).Value = src.Cells(i, 6).Value rep.Cells(outRow, 6).Value = src.Cells(i, 7).Value rep.Cells(outRow, 7).Value = src.Cells(i, 7).Value - src.Cells(i, 6).Value rep.Cells(outRow, 8).Value = pct If pct > 0 Then rep.Cells(outRow, 8).Interior.Color = RGB(250, 219, 216) Else rep.Cells(outRow, 8).Interior.Color = RGB(213, 245, 227) End If outRow = outRow + 1 End If End If Next i rep.Range("E:G").NumberFormat = "$#,##0" rep.Range("H:H").NumberFormat = "0.0%" rep.Columns("B:H").AutoFit MsgBox (outRow - 5) & " variance exceptions written to Variance_Exceptions sheet.", vbInformation End Sub
