Workbook

Sheet Cover
B2: PORTFOLIO REBALANCER
B3: Risk-Based Allocation · Target Glide Path · Rebalance Trade List
B5: Risk-profile-driven portfolio rebalancer for a 6-asset strategic portfolio (Canadian Equity, US Equity, International Equity, Canadian Fixed Income, Global Fixed Income, Cash). The target allocation is selected via a dropdown (Conservative / Balanced / Growth / Aggressive) and retrieved via HLOOKUP. Current holdings drift is compared to target, expected portfolio return and volatility are computed via SUMPRODUCT, and a VBA macro generates a ready-to-execute trade list (Buy / Sell / Hold with dollar amounts) to bring the portfolio back to target. Maps directly to the CIFC, FMVA®, and CBCA® toolkit.

Sheet Targets
B2: TARGET ALLOCATION MATRIX (HLOOKUP source)
B3: Asset Class | C3: Conservative | D3: Balanced | E3: Growth | F3: Aggressive | G3: Expected Return | H3: Volatility
B4: Canadian Equity | C4: 0.1 | D4: 0.2 | E4: 0.25 | F4: 0.3 | G4: 0.075 | H4: 0.16
B5: US Equity | C5: 0.1 | D5: 0.2 | E5: 0.3 | F5: 0.35 | G5: 0.09 | H5: 0.17
B6: International Equity | C6: 0.05 | D6: 0.1 | E6: 0.15 | F6: 0.2 | G6: 0.08 | H6: 0.18
B7: Canadian Fixed Income | C7: 0.45 | D7: 0.3 | E7: 0.15 | F7: 0.08 | G7: 0.035 | H7: 0.05
B8: Global Fixed Income | C8: 0.2 | D8: 0.15 | E8: 0.1 | F8: 0.05 | G8: 0.04 | H8: 0.06
B9: Cash | C9: 0.1 | D9: 0.05 | E9: 0.05 | F9: 0.02 | G9: 0.02 | H9: 0.005
B10: Total | C10: =SUM(C4:C9) -> 1 | D10: =SUM(D4:D9) -> 1 | E10: =SUM(E4:E9) -> 1 | F10: =SUM(F4:F9) -> 1

Sheet Inputs
B2: PORTFOLIO INPUTS
B4: Portfolio Value ($) | C4: 500000
B5: Risk Profile | C5: Growth
B6: Rebalance Threshold | C6: 0.03

Sheet Analysis
B2: PORTFOLIO ANALYSIS & DRIFT
B4: Asset Class | C4: Current $ | D4: Current % | E4: Target % | F4: Target $ | G4: Drift % | H4: Action
B5: Canadian Equity | C5: 175000 | D5: =C5/SUM($C$5:$C$10) -> 0.35 | E5: =INDEX(Targets!$C$4:$F$9, MATCH(B5, Targets!$B$4:$B$9, 0), MATCH(RiskProf, Targets!$C$3:$F$3, 0)) -> 0.25 | F5: =E5*PortValue -> 125000 | G5: =D5-E5 -> 0.1 | H5: =IF(ABS(G5)<=ReBalThresh,"HOLD",IF(G5>0,"SELL","BUY")) -> SELL
B6: US Equity | C6: 140000 | D6: =C6/SUM($C$5:$C$10) -> 0.28 | E6: =INDEX(Targets!$C$4:$F$9, MATCH(B6, Targets!$B$4:$B$9, 0), MATCH(RiskProf, Targets!$C$3:$F$3, 0)) -> 0.3 | F6: =E6*PortValue -> 150000 | G6: =D6-E6 -> -0.02 | H6: =IF(ABS(G6)<=ReBalThresh,"HOLD",IF(G6>0,"SELL","BUY")) -> HOLD
B7: International Equity | C7: 40000 | D7: =C7/SUM($C$5:$C$10) -> 0.08 | E7: =INDEX(Targets!$C$4:$F$9, MATCH(B7, Targets!$B$4:$B$9, 0), MATCH(RiskProf, Targets!$C$3:$F$3, 0)) -> 0.15 | F7: =E7*PortValue -> 75000 | G7: =D7-E7 -> -0.07 | H7: =IF(ABS(G7)<=ReBalThresh,"HOLD",IF(G7>0,"SELL","BUY")) -> BUY
B8: Canadian Fixed Income | C8: 85000 | D8: =C8/SUM($C$5:$C$10) -> 0.17 | E8: =INDEX(Targets!$C$4:$F$9, MATCH(B8, Targets!$B$4:$B$9, 0), MATCH(RiskProf, Targets!$C$3:$F$3, 0)) -> 0.15 | F8: =E8*PortValue -> 75000 | G8: =D8-E8 -> 0.02 | H8: =IF(ABS(G8)<=ReBalThresh,"HOLD",IF(G8>0,"SELL","BUY")) -> HOLD
B9: Global Fixed Income | C9: 40000 | D9: =C9/SUM($C$5:$C$10) -> 0.08 | E9: =INDEX(Targets!$C$4:$F$9, MATCH(B9, Targets!$B$4:$B$9, 0), MATCH(RiskProf, Targets!$C$3:$F$3, 0)) -> 0.1 | F9: =E9*PortValue -> 50000 | G9: =D9-E9 -> -0.02 | H9: =IF(ABS(G9)<=ReBalThresh,"HOLD",IF(G9>0,"SELL","BUY")) -> HOLD
B10: Cash | C10: 20000 | D10: =C10/SUM($C$5:$C$10) -> 0.04 | E10: =INDEX(Targets!$C$4:$F$9, MATCH(B10, Targets!$B$4:$B$9, 0), MATCH(RiskProf, Targets!$C$3:$F$3, 0)) -> 0.05 | F10: =E10*PortValue -> 25000 | G10: =D10-E10 -> -0.01 | H10: =IF(ABS(G10)<=ReBalThresh,"HOLD",IF(G10>0,"SELL","BUY")) -> HOLD
B11: Total | C11: =SUM(C5:C10) -> 500000 | D11: =SUM(D5:D10) -> 1 | E11: =SUM(E5:E10) -> 1 | F11: =SUM(F5:F10) -> 500000
B13: PORTFOLIO STATISTICS (SUMPRODUCT)
B14: Expected Return (current) | C14: =SUMPRODUCT(D5:D10, Targets!G4:G9) -> 0.0678
B15: Expected Return (target) | C15: =SUMPRODUCT(E5:E10, Targets!G4:G9) -> 0.068
B16: Weighted Volatility (current) | C16: =SUMPRODUCT(D5:D10, Targets!H4:H9) -> 0.1315
B17: Weighted Volatility (target) | C17: =SUMPRODUCT(E5:E10, Targets!H4:H9) -> 0.13175
B18: Return / Vol (Sharpe-like) | C18: =C15/C17 -> 0.51612903

Sheet VBA_Code
B2: VBA MACROS — Trade List Generator
B3: Import RebalanceMacros.bas via Alt+F11 → File → Import File.
B5: Option Explicit ' ============================================================ ' RebalanceMacros.bas — Kartik Joshi ' Portfolio rebalancer — generate executable trade list ' ============================================================ Public Sub GenerateTradeList() Dim an As Worksheet, tl As Worksheet, i As Long, outRow As Long Dim action As String, tradeAmt As Double, totalBuys As Double, totalSells As Double Set an = ThisWorkbook.Worksheets("Analysis") On Error Resume Next Application.DisplayAlerts = False ThisWorkbook.Worksheets("TradeList").Delete Application.DisplayAlerts = True On Error GoTo 0 Set tl = ThisWorkbook.Worksheets.Add(After:= _ ThisWorkbook.Worksheets(ThisWorkbook.Worksheets.Count)) tl.Name = "TradeList" tl.Range("B2").Value = "REBALANCING TRADE LIST — " & Format(Now, "yyyy-mm-dd hh:nn") tl.Range("B2").Font.Bold = True tl.Range("B2").Font.Size = 14 Dim headers As Variant headers = Array("Asset Class", "Action", "Current $", "Target $", "Trade $", "Drift %") Dim j As Integer For j = LBound(headers) To UBound(headers) tl.Cells(4, 2 + j).Value = headers(j) tl.Cells(4, 2 + j).Font.Bold = True tl.Cells(4, 2 + j).Interior.Color = RGB(27, 42, 73) tl.Cells(4, 2 + j).Font.Color = RGB(255, 255, 255) Next j outRow = 5 For i = 5 To 10 action = CStr(an.Cells(i, 8).Value) tradeAmt = an.Cells(i, 6).Value - an.Cells(i, 3).Value ' target - current tl.Cells(outRow, 2).Value = an.Cells(i, 2).Value tl.Cells(outRow, 3).Value = action tl.Cells(outRow, 4).Value = an.Cells(i, 3).Value tl.Cells(outRow, 5).Value = an.Cells(i, 6).Value tl.Cells(outRow, 6).Value = tradeAmt tl.Cells(outRow, 7).Value = an.Cells(i, 7).Value If action = "BUY" Then tl.Cells(outRow, 3).Interior.Color = RGB(213, 245, 227) totalBuys = totalBuys + tradeAmt ElseIf action = "SELL" Then tl.Cells(outRow, 3).Interior.Color = RGB(250, 219, 216) totalSells = totalSells + Abs(tradeAmt) Else tl.Cells(outRow, 3).Interior.Color = RGB(234, 242, 248) End If outRow = outRow + 1 Next i ' Summary tl.Cells(outRow + 1, 2).Value = "Summary" tl.Cells(outRow + 1, 2).Font.Bold = True tl.Cells(outRow + 2, 2).Value = "Total Buys" tl.Cells(outRow + 2, 3).Value = totalBuys tl.Cells(outRow + 3, 2).Value = "Total Sells" tl.Cells(outRow + 3, 3).Value = totalSells tl.Cells(outRow + 4, 2).Value = "Net (should be ~0)" tl.Cells(outRow + 4, 3).Value = totalBuys - totalSells tl.Range("D5:F" & outRow + 4).NumberFormat = "$#,##0;($#,##0);-" tl.Range("G5:G" & outRow - 1).NumberFormat = "0.0%;-0.0%" tl.Columns("B:G").AutoFit MsgBox "Trade list generated." & vbCrLf & _ "Buys: " & Format(totalBuys, "$#,##0") & vbCrLf & _ "Sells: " & Format(totalSells, "$#,##0"), vbInformation End Sub Public Sub ApplyRebalance() Dim resp As VbMsgBoxResult, an As Worksheet, i As Long resp = MsgBox("This will overwrite Current $ with Target $ values. Continue?", _ vbYesNo + vbQuestion, "Apply Rebalance") If resp <> vbYes Then Exit Sub Set an = ThisWorkbook.Worksheets("Analysis") For i = 5 To 10 an.Cells(i, 3).Value = an.Cells(i, 6).Value Next i Application.Calculate MsgBox "Portfolio rebalanced to target allocation.", vbInformation End Sub
